{"skeleton":{"hash":"FimPjSBxOBksu8UzEpOL6zVs4Oo","spine":"3.7.94","width":300,"height":156.89,"images":"E:/输出/快速组局1/","audio":""},"bones":[{"name":"root"},{"name":"bone","parent":"root","length":17.12,"rotation":88.7,"x":10.84,"y":40.89}],"slots":[{"name":"快速组局1_00000","bone":"root","attachment":"k9"},{"name":"快速组局2_00000","bone":"bone","attachment":"l9"}],"skins":{"default":{"快速组局1_00000":{"k1":{"y":0.5,"width":300,"height":149},"k2":{"y":0.5,"width":300,"height":149},"k3":{"y":0.5,"width":300,"height":149},"k4":{"y":0.5,"width":300,"height":149},"k5":{"y":0.5,"width":300,"height":149},"k6":{"y":0.5,"width":300,"height":149},"k7":{"y":0.5,"width":300,"height":149},"k8":{"y":0.5,"width":300,"height":149},"k9":{"y":0.5,"width":300,"height":149},"k10":{"y":0.5,"width":300,"height":149},"k11":{"y":0.5,"width":300,"height":149},"k12":{"y":0.5,"width":300,"height":149},"k13":{"y":0.5,"width":300,"height":149}},"快速组局2_00000":{"l1":{"x":0.51,"y":-0.49,"rotation":-88.7,"width":195,"height":83},"l2":{"x":0.51,"y":-0.49,"rotation":-88.7,"width":195,"height":83},"l3":{"x":0.51,"y":-0.49,"rotation":-88.7,"width":195,"height":83},"l4":{"x":0.51,"y":-0.49,"rotation":-88.7,"width":195,"height":83},"l5":{"x":0.51,"y":-0.49,"rotation":-88.7,"width":195,"height":83},"l6":{"x":0.51,"y":-0.49,"rotation":-88.7,"width":195,"height":83},"l7":{"x":0.51,"y":-0.49,"rotation":-88.7,"width":195,"height":83},"l8":{"x":0.51,"y":-0.49,"rotation":-88.7,"width":195,"height":83},"l9":{"x":0.51,"y":-0.49,"rotation":-88.7,"width":195,"height":83},"l10":{"x":0.51,"y":-0.49,"rotation":-88.7,"width":195,"height":83},"l11":{"x":0.51,"y":-0.49,"rotation":-88.7,"width":195,"height":83},"l12":{"x":0.51,"y":-0.49,"rotation":-88.7,"width":195,"height":83},"l13":{"x":0.51,"y":-0.49,"rotation":-88.7,"width":195,"height":83}}}},"animations":{"animation":{"slots":{"快速组局1_00000":{"attachment":[{"time":0,"name":"k1"},{"time":0.0667,"name":"k2"},{"time":0.1333,"name":"k3"},{"time":0.2,"name":"k4"},{"time":0.2667,"name":"k5"},{"time":0.3333,"name":"k6"},{"time":0.4,"name":"k7"},{"time":0.4667,"name":"k8"},{"time":0.5333,"name":"k9"},{"time":0.6,"name":"k10"},{"time":0.7,"name":"k11"},{"time":0.8,"name":"k12"},{"time":0.9,"name":"k13"}]},"快速组局2_00000":{"attachment":[{"time":0,"name":"l1"},{"time":0.0667,"name":"l2"},{"time":0.1333,"name":"l3"},{"time":0.2,"name":"l4"},{"time":0.2667,"name":"l5"},{"time":0.3333,"name":"l6"},{"time":0.4,"name":"l7"},{"time":0.4667,"name":"l8"},{"time":0.5333,"name":"l9"},{"time":0.6,"name":"l10"},{"time":0.7,"name":"l11"},{"time":0.8,"name":"l12"},{"time":0.9,"name":"l13"}]}}}}}